wsireg/__init__.py
wsireg/wsireg2d.py
wsireg/parameter_maps/__init__.py
wsireg/parameter_maps/preprocessing.py
wsireg/parameter_maps/reg_model.py
wsireg/parameter_maps/reg_params.py
wsireg/parameter_maps/transformations.py
wsireg/reg_images/__init__.py
wsireg/reg_images/czi_reg_image.py
wsireg/reg_images/loader.py
wsireg/reg_images/merge_reg_image.py
wsireg/reg_images/np_reg_image.py
wsireg/reg_images/reg_image.py
wsireg/reg_images/sitk_reg_image.py
wsireg/reg_images/tifffile_reg_image.py
wsireg/reg_shapes/__init__.py
wsireg/reg_shapes/reg_shapes.py
wsireg/reg_transforms/__init__.py
wsireg/reg_transforms/reg_transform.py
wsireg/reg_transforms/reg_transform_seq.py
wsireg/utils/__init__.py
wsireg/utils/config_utils.py
wsireg/utils/im_utils.py
wsireg/utils/itk_im_conversions.py
wsireg/utils/output_utils.py
wsireg/utils/reg_utils.py
wsireg/utils/shape_utils.py
wsireg/utils/tform_conversion.py
wsireg/utils/tform_utils.py
wsireg/writers/__init__.py
wsireg/writers/merge_ome_tiff_writer.py
wsireg/writers/ome_tiff_writer.py
wsireg/writers/tiled_ome_tiff_writer.py
wsireg-0.3.10.dist-info/AUTHORS.rst
wsireg-0.3.10.dist-info/LICENSE
wsireg-0.3.10.dist-info/METADATA
wsireg-0.3.10.dist-info/WHEEL
wsireg-0.3.10.dist-info/entry_points.txt
wsireg-0.3.10.dist-info/top_level.txt
wsireg-0.3.10.dist-info/RECORD
