Metadata-Version: 2.1
Name: wsireg
Version: 0.3.10
Summary: python package for registering multimodal whole slide microscopy images
Home-page: https://github.com/nhpatterson/wsireg
Author: Nathan Heath Patterson
Author-email: heath.patterson@vanderbilt.edu
License: MIT license
Keywords: wsireg
Classifier: Development Status :: 4 - Beta
Classifier: Intended Audience :: Science/Research
Classifier: License :: OSI Approved :: MIT License
Classifier: Natural Language :: English
Classifier: Programming Language :: Python :: 3
Classifier: Programming Language :: Python :: 3.9
Classifier: Programming Language :: Python :: 3.10
Classifier: Programming Language :: Python :: 3.11
Requires-Python: >=3.8
License-File: LICENSE
License-File: AUTHORS.rst
Requires-Dist: numpy
Requires-Dist: tifffile >=2022.2.9
Requires-Dist: zarr >=2.11.0
Requires-Dist: opencv-python-headless
Requires-Dist: czifile
Requires-Dist: imagecodecs
Requires-Dist: lxml
Requires-Dist: geojson
Requires-Dist: pyYAML
Requires-Dist: toolz
Requires-Dist: dask
Requires-Dist: fsspec
Requires-Dist: itk-elastix
Requires-Dist: SimpleITK
Requires-Dist: pydantic >=2.6.4
Requires-Dist: ome-types >=0.5.1
Requires-Dist: tiler
Requires-Dist: tqdm
Requires-Dist: matplotlib
